swordfish/__init__.py
swordfish_pro-0.0.1.dist-info/METADATA
swordfish_pro-0.0.1.dist-info/WHEEL
swordfish_pro-0.0.1.dist-info/RECORD
